algorizer/__init__.py
algorizer/active.py
algorizer/candle.py
algorizer/client.py
algorizer/console.py
algorizer/constants.py
algorizer/fetcher.py
algorizer/pivots.py
algorizer/series.py
algorizer/server.py
algorizer/stream.py
algorizer/ta.py
algorizer/tasks.py
algorizer/tools.py
algorizer/trade.py
algorizer-0.1.1.dist-info/licenses/LICENSE
algorizer-0.1.1.dist-info/METADATA
algorizer-0.1.1.dist-info/WHEEL
algorizer-0.1.1.dist-info/top_level.txt
algorizer-0.1.1.dist-info/RECORD
