Metadata-Version: 2.4
Name: algorizer
Version: 0.1.1
Summary: A framework for algorithmic strategy scripts.
Author-email: Germán García <germangarciaart@gmail.com>
License: MIT License
Requires-Python: >=3.8
License-File: LICENSE
Requires-Dist: pandas>=2.0.0
Requires-Dist: numpy>=1.26.0
Requires-Dist: ccxt>=4.4.77
Requires-Dist: pyzmq>=25.0.0
Requires-Dist: requests>=2.31.0
Requires-Dist: msgpack>=1.0.0
Requires-Dist: lightweight-charts>=2.1
Requires-Dist: aioconsole>=0.6.0
Requires-Dist: colorama~=0.4.6
Dynamic: license-file
